cs_demand_model/__init__.py
cs_demand_model/__main__.py
cs_demand_model/config/__init__.py
cs_demand_model/config/_age_brackets.py
cs_demand_model/config/_configuration_loader.py
cs_demand_model/config/_configuration_source.py
cs_demand_model/config/_costs.py
cs_demand_model/config/_placement_categories.py
cs_demand_model/data/__init__.py
cs_demand_model/data/ssda903/__init__.py
cs_demand_model/datacontainer.py
cs_demand_model/datastore/__init__.py
cs_demand_model/datastore/_api.py
cs_demand_model/datastore/_fs.py
cs_demand_model/datastore/_opener.py
cs_demand_model/datastore/_sample.py
cs_demand_model/datastore/_zip.py
cs_demand_model/fixtures/__init__.py
cs_demand_model/fixtures/config/__init__.py
cs_demand_model/fixtures/config/standard-v1.yaml
cs_demand_model/population_stats.py
cs_demand_model/prediction.py
cs_demand_model/rpc/__init__.py
cs_demand_model/rpc/api.py
cs_demand_model/rpc/components.py
cs_demand_model/rpc/figs/__init__.py
cs_demand_model/rpc/figs/costs.py
cs_demand_model/rpc/figs/forecast.py
cs_demand_model/rpc/figs/placeholder.py
cs_demand_model/rpc/figs/util.py
cs_demand_model/rpc/forms/__init__.py
cs_demand_model/rpc/forms/adjustments.py
cs_demand_model/rpc/forms/cost_proportions.py
cs_demand_model/rpc/forms/costs.py
cs_demand_model/rpc/forms/model_dates.py
cs_demand_model/rpc/state.py
cs_demand_model/rpc/types.py
cs_demand_model/rpc/util.py
cs_demand_model/rpc/views/__init__.py
cs_demand_model/rpc/views/charts.py
cs_demand_model/rpc/views/datastore.py
cs_demand_model_samples/__init__.py
cs_demand_model_samples/combined/2017-ad1.csv
cs_demand_model_samples/combined/2017-episodes.csv
cs_demand_model_samples/combined/2017-header.csv
cs_demand_model_samples/combined/2017-missing.csv
cs_demand_model_samples/combined/2017-oc2.csv
cs_demand_model_samples/combined/2017-oc3.csv
cs_demand_model_samples/combined/2017-placed_for_adoption.csv
cs_demand_model_samples/combined/2017-previous_permanence.csv
cs_demand_model_samples/combined/2017-reviews.csv
cs_demand_model-0.5.1.dist-info/LICENSE
cs_demand_model-0.5.1.dist-info/METADATA
cs_demand_model-0.5.1.dist-info/WHEEL
cs_demand_model-0.5.1.dist-info/entry_points.txt
cs_demand_model-0.5.1.dist-info/RECORD
